module/__init__.py
module_Thw-0.0.6.dist-info/LICENSE.txt
module_Thw-0.0.6.dist-info/METADATA
module_Thw-0.0.6.dist-info/WHEEL
module_Thw-0.0.6.dist-info/top_level.txt
module_Thw-0.0.6.dist-info/RECORD
