Metadata-Version: 2.1
Name: module-Thw
Version: 0.0.6
Summary: some module
Home-page: https://github.com/Thachj-Thw/module
Author: Thw
Author-email: 
Project-URL: Source, https://github.com/Thachj-Thw/module
Keywords: module
Classifier: Development Status :: 5 - Production/Stable
Classifier: Programming Language :: Python :: 3
Classifier: License :: OSI Approved :: MIT License
Classifier: Operating System :: Microsoft :: Windows
Classifier: Natural Language :: Vietnamese
Requires-Python: >=3.6
License-File: LICENSE.txt
Requires-Dist: pywin32
